meprpo/__init__.py
meprpo/meprpo.py
meprpo/neo4j_calculate_correlations.py
meprpo/neo4j_connector.py
meprpo/neo4j_correlation_heatmaps.py
meprpo/neo4j_display_distances.py
meprpo/neo4j_display_edges.py
meprpo/neo4j_fetch_data.py
meprpo/neo4j_fetch_paths.py
meprpo-0.1.2.dist-info/licenses/LICENSE
meprpo-0.1.2.dist-info/METADATA
meprpo-0.1.2.dist-info/WHEEL
meprpo-0.1.2.dist-info/top_level.txt
meprpo-0.1.2.dist-info/RECORD
