Metadata-Version: 2.4
Name: meprpo
Version: 0.1.2
Summary: Measuring predictive potential in graph databases
Home-page: https://github.com/Jozef-Lauko/Measuring-predictive-potential-in-graph-databases
Author: Jozef Lauko
Author-email: laukojozef1@gmail.com
Classifier: Programming Language :: Python :: 3
Classifier: License :: OSI Approved :: MIT License
Classifier: Operating System :: OS Independent
Requires-Python: >=3.7
License-File: LICENSE
Requires-Dist: neo4j
Requires-Dist: numpy
Requires-Dist: pandas
Requires-Dist: matplotlib
Requires-Dist: scipy
Requires-Dist: requests
Dynamic: author
Dynamic: author-email
Dynamic: classifier
Dynamic: description
Dynamic: description-content-type
Dynamic: home-page
Dynamic: license-file
Dynamic: requires-dist
Dynamic: requires-python
Dynamic: summary
